{

"certificate": {

  "cluster" : "rasp_db",
  "ui" : false,
  "api" : true,
  "fields" : {
    "id": {

     "name" : "id",
     "required" : "true",
     "type" : "String"
     },
    "course_name": {

     "name" : "course_name",
     "required" : "true",
     "type" : "String"
     },
    "course_duration": {

     "name" : "course_duration",
     "required" : "true",
     "type" : "Long"
     },
    "course_mode": {

     "name" : "course_mode",
     "required" : "true",
     "is_enum" : "true",
      "possible_value" : "Course_mode",
     "type" : "String"
     },
    "platform": {

     "name" : "platform",
     "required" : "true",
     "type" : "String"
     },
    "course_completion_date": {

     "name" : "course_completion_date",
     "required" : "true",
     "type" : "Date"
     },
    "upload_certificate": {

     "name" : "upload_certificate",
     "required" : "true",
     "is_file" : "true",
     "type" : "String"
     },
    "status": {

     "name" : "status",
     "required" : "false",
     "type" : "Boolean"
     },
    "student_id": {

     "name" : "student_id",
     "required" : "true",
     "foreign" : {
      "resource" : "Student" 
      },
     "type" : "String"
     },
    "course_url": {

     "name" : "course_url",
     "required" : "false",
     "type" : "String"
      }
   
  }
 }

}

